{"name": "100__5001", "children": [{"name": "109__5002", "children": [{"name": "106__5007", "children": [{"name": "102__5026", "children": [{"children": [], "name": "105__5070", "size": 1}]}]}, {"name": "101__5008", "children": [{"name": "100__5027", "children": [{"name": "107__5071", "children": [{"children": [], "name": "108__5127", "size": 1}, {"name": "104__5128", "children": [{"children": [], "name": "106__5178", "size": 1}, {"name": "103__5179", "children": [{"name": "108__5217", "children": [{"children": [], "name": "100__5248", "size": 1}, {"children": [], "name": "109__5249", "size": 1}]}]}]}]}]}, {"name": "108__5028", "children": [{"children": [], "name": "106__5072", "size": 1}]}, {"name": "109__5029", "children": [{"name": "103__5073", "children": [{"name": "109__5129", "children": [{"name": "104__5180", "children": [{"children": [], "name": "108__5218", "size": 1}, {"name": "106__5219", "children": [{"children": [], "name": "109__5250", "size": 1}]}]}]}]}]}]}, {"name": "107__5009", "children": [{"children": [], "name": "105__5030", "size": 1}, {"name": "100__5031", "children": [{"name": "108__5074", "children": [{"name": "107__5130", "children": [{"children": [], "name": "103__5181", "size": 1}, {"children": [], "name": "105__5182", "size": 1}]}, {"name": "100__5131", "children": [{"name": "108__5183", "children": [{"name": "100__5220", "children": [{"children": [], "name": "104__5251", "size": 1}, {"children": [], "name": "105__5252", "size": 1}]}]}]}]}]}, {"children": [], "name": "106__5032", "size": 1}, {"name": "103__5033", "children": [{"children": [], "name": "107__5075", "size": 1}]}]}, {"name": "108__5010", "children": [{"name": "106__5034", "children": [{"name": "104__5076", "children": [{"children": [], "name": "100__5132", "size": 1}]}, {"children": [], "name": "101__5077", "size": 1}, {"name": "102__5078", "children": [{"name": "101__5133", "children": [{"children": [], "name": "105__5184", "size": 1}]}, {"children": [], "name": "103__5134", "size": 1}]}]}, {"name": "100__5035", "children": [{"children": [], "name": "102__5079", "size": 1}, {"children": [], "name": "103__5080", "size": 1}]}]}]}, {"name": "105__5003", "children": [{"children": [], "name": "108__5011", "size": 1}, {"name": "101__5012", "children": [{"name": "108__5036", "children": [{"name": "109__5081", "children": [{"name": "104__5135", "children": [{"children": [], "name": "100__5185", "size": 1}, {"name": "106__5186", "children": [{"children": [], "name": "104__5221", "size": 1}]}]}]}]}, {"children": [], "name": "107__5037", "size": 1}]}, {"name": "103__5013", "children": [{"name": "109__5038", "children": [{"children": [], "name": "103__5082", "size": 1}, {"name": "101__5083", "children": [{"name": "103__5136", "children": [{"children": [], "name": "106__5187", "size": 1}]}, {"name": "108__5137", "children": [{"children": [], "name": "100__5188", "size": 1}, {"name": "109__5189", "children": [{"name": "101__5222", "children": [{"children": [], "name": "104__5253", "size": 1}]}]}]}]}]}, {"name": "107__5039", "children": [{"name": "100__5084", "children": [{"children": [], "name": "101__5138", "size": 1}]}, {"name": "109__5085", "children": [{"name": "100__5139", "children": [{"name": "102__5190", "children": [{"name": "106__5223", "children": [{"children": [], "name": "101__5254", "size": 1}]}]}]}]}]}, {"children": [], "name": "101__5040", "size": 1}, {"name": "106__5041", "children": [{"children": [], "name": "104__5086", "size": 1}, {"name": "107__5087", "children": [{"children": [], "name": "109__5140", "size": 1}, {"name": "103__5141", "children": [{"name": "102__5191", "children": [{"children": [], "name": "107__5224", "size": 1}, {"name": "104__5225", "children": [{"children": [], "name": "102__5255", "size": 1}]}]}]}]}]}]}]}, {"name": "101__5004", "children": [{"name": "102__5014", "children": [{"name": "108__5042", "children": [{"name": "106__5088", "children": [{"children": [], "name": "107__5142", "size": 1}]}, {"name": "103__5089", "children": [{"name": "104__5143", "children": [{"name": "100__5192", "children": [{"name": "109__5226", "children": [{"children": [], "name": "102__5256", "size": 1}]}, {"children": [], "name": "102__5227", "size": 1}]}]}]}, {"children": [], "name": "104__5090", "size": 1}]}, {"name": "109__5043", "children": [{"name": "107__5091", "children": [{"children": [], "name": "101__5144", "size": 1}, {"name": "103__5145", "children": [{"name": "107__5193", "children": [{"children": [], "name": "100__5228", "size": 1}]}]}]}, {"name": "105__5092", "children": [{"children": [], "name": "102__5146", "size": 1}]}]}, {"children": [], "name": "101__5044", "size": 1}]}, {"name": "103__5015", "children": [{"name": "105__5045", "children": [{"name": "103__5093", "children": [{"name": "105__5147", "children": [{"name": "101__5194", "children": [{"name": "103__5229", "children": [{"children": [], "name": "109__5257", "size": 1}, {"children": [], "name": "104__5258", "size": 1}]}]}, {"name": "103__5195", "children": [{"children": [], "name": "107__5230", "size": 1}, {"name": "106__5231", "children": [{"children": [], "name": "102__5259", "size": 1}]}]}]}]}]}]}, {"name": "105__5016", "children": [{"name": "107__5046", "children": [{"name": "104__5094", "children": [{"children": [], "name": "101__5148", "size": 1}]}, {"name": "103__5095", "children": [{"name": "109__5149", "children": [{"name": "104__5196", "children": [{"name": "109__5232", "children": [{"children": [], "name": "103__5260", "size": 1}, {"children": [], "name": "102__5261", "size": 1}]}]}]}]}]}]}, {"name": "109__5017", "children": [{"name": "104__5047", "children": [{"name": "100__5096", "children": [{"name": "103__5150", "children": [{"name": "108__5197", "children": [{"children": [], "name": "103__5233", "size": 1}, {"children": [], "name": "105__5234", "size": 1}]}]}]}, {"name": "101__5097", "children": [{"name": "105__5151", "children": [{"name": "104__5198", "children": [{"children": [], "name": "105__5235", "size": 1}]}, {"name": "103__5199", "children": [{"name": "106__5236", "children": [{"children": [], "name": "100__5262", "size": 1}]}]}]}]}]}, {"name": "108__5048", "children": [{"name": "101__5098", "children": [{"children": [], "name": "105__5152", "size": 1}]}, {"name": "104__5099", "children": [{"children": [], "name": "106__5153", "size": 1}]}, {"children": [], "name": "100__5100", "size": 1}]}]}]}, {"name": "108__5005", "children": [{"name": "105__5018", "children": [{"name": "103__5049", "children": [{"name": "104__5101", "children": [{"children": [], "name": "107__5154", "size": 1}]}]}, {"name": "101__5050", "children": [{"children": [], "name": "108__5102", "size": 1}, {"name": "104__5103", "children": [{"name": "105__5155", "children": [{"name": "106__5200", "children": [{"children": [], "name": "102__5237", "size": 1}, {"children": [], "name": "108__5238", "size": 1}]}, {"children": [], "name": "109__5201", "size": 1}]}, {"children": [], "name": "100__5156", "size": 1}]}]}, {"name": "109__5051", "children": [{"children": [], "name": "100__5104", "size": 1}]}]}, {"name": "106__5019", "children": [{"children": [], "name": "108__5052", "size": 1}, {"name": "100__5053", "children": [{"children": [], "name": "102__5105", "size": 1}]}, {"name": "105__5054", "children": [{"name": "104__5106", "children": [{"children": [], "name": "106__5157", "size": 1}]}, {"children": [], "name": "109__5107", "size": 1}]}, {"name": "103__5055", "children": [{"name": "109__5108", "children": [{"children": [], "name": "102__5158", "size": 1}]}]}]}, {"name": "101__5020", "children": [{"children": [], "name": "104__5056", "size": 1}, {"name": "107__5057", "children": [{"name": "109__5109", "children": [{"children": [], "name": "102__5159", "size": 1}]}, {"children": [], "name": "103__5110", "size": 1}]}, {"name": "100__5058", "children": [{"name": "105__5111", "children": [{"name": "101__5160", "children": [{"children": [], "name": "100__5202", "size": 1}, {"children": [], "name": "106__5203", "size": 1}]}]}]}]}, {"children": [], "name": "104__5021", "size": 1}, {"name": "103__5022", "children": [{"name": "109__5059", "children": [{"name": "107__5112", "children": [{"name": "109__5161", "children": [{"name": "108__5204", "children": [{"name": "109__5239", "children": [{"children": [], "name": "106__5263", "size": 1}, {"children": [], "name": "107__5264", "size": 1}]}, {"name": "100__5240", "children": [{"children": [], "name": "102__5265", "size": 1}]}]}]}, {"name": "100__5162", "children": [{"children": [], "name": "105__5205", "size": 1}]}]}, {"name": "100__5113", "children": [{"children": [], "name": "102__5163", "size": 1}]}, {"name": "108__5114", "children": [{"children": [], "name": "102__5164", "size": 1}]}]}, {"name": "101__5060", "children": [{"name": "102__5115", "children": [{"name": "104__5165", "children": [{"children": [], "name": "101__5206", "size": 1}, {"children": [], "name": "102__5207", "size": 1}]}]}]}, {"name": "105__5061", "children": [{"children": [], "name": "104__5116", "size": 1}]}]}]}, {"name": "103__5006", "children": [{"name": "106__5023", "children": [{"name": "103__5062", "children": [{"name": "108__5117", "children": [{"children": [], "name": "109__5166", "size": 1}]}, {"name": "107__5118", "children": [{"children": [], "name": "104__5167", "size": 1}, {"name": "109__5168", "children": [{"name": "105__5208", "children": [{"name": "101__5241", "children": [{"children": [], "name": "108__5266", "size": 1}]}]}, {"children": [], "name": "103__5209", "size": 1}]}]}]}]}, {"name": "100__5024", "children": [{"name": "105__5063", "children": [{"name": "102__5119", "children": [{"name": "109__5169", "children": [{"children": [], "name": "100__5210", "size": 1}, {"name": "105__5211", "children": [{"name": "103__5242", "children": [{"children": [], "name": "106__5267", "size": 1}, {"children": [], "name": "105__5268", "size": 1}]}]}]}]}, {"name": "100__5120", "children": [{"name": "106__5170", "children": [{"name": "108__5212", "children": [{"children": [], "name": "101__5243", "size": 1}]}]}]}, {"name": "109__5121", "children": [{"name": "108__5171", "children": [{"name": "100__5213", "children": [{"name": "109__5244", "children": [{"children": [], "name": "105__5269", "size": 1}, {"children": [], "name": "104__5270", "size": 1}]}, {"name": "101__5245", "children": [{"children": [], "name": "102__5271", "size": 1}, {"children": [], "name": "109__5272", "size": 1}]}]}]}, {"children": [], "name": "103__5172", "size": 1}]}]}, {"children": [], "name": "106__5064", "size": 1}, {"name": "107__5065", "children": [{"children": [], "name": "100__5122", "size": 1}]}, {"children": [], "name": "101__5066", "size": 1}]}, {"name": "108__5025", "children": [{"children": [], "name": "104__5067", "size": 1}, {"name": "100__5068", "children": [{"name": "104__5123", "children": [{"name": "103__5173", "children": [{"children": [], "name": "108__5214", "size": 1}]}]}, {"name": "103__5124", "children": [{"children": [], "name": "107__5174", "size": 1}]}]}, {"name": "109__5069", "children": [{"name": "104__5125", "children": [{"name": "107__5175", "children": [{"children": [], "name": "101__5215", "size": 1}]}]}, {"name": "107__5126", "children": [{"children": [], "name": "106__5176", "size": 1}, {"name": "108__5177", "children": [{"name": "105__5216", "children": [{"name": "106__5246", "children": [{"children": [], "name": "107__5273", "size": 1}]}, {"name": "109__5247", "children": [{"children": [], "name": "107__5274", "size": 1}, {"children": [], "name": "104__5275", "size": 1}]}]}]}]}]}]}]}]}